panko/__init__.py
panko/i18n.py
panko/opts.py
panko/profiler.py
panko/service.py
panko/utils.py
panko/version.py
panko/api/__init__.py
panko/api/app.py
panko/api/app.wsgi
panko/api/hooks.py
panko/api/middleware.py
panko/api/rbac.py
panko/api/controllers/__init__.py
panko/api/controllers/root.py
panko/api/controllers/v2/__init__.py
panko/api/controllers/v2/base.py
panko/api/controllers/v2/capabilities.py
panko/api/controllers/v2/events.py
panko/api/controllers/v2/root.py
panko/api/controllers/v2/utils.py
panko/cmd/__init__.py
panko/cmd/storage.py
panko/conf/__init__.py
panko/conf/defaults.py
panko/hacking/__init__.py
panko/hacking/checks.py
panko/locale/en_GB/LC_MESSAGES/panko.po
panko/locale/ko_KR/LC_MESSAGES/panko.po
panko/policies/__init__.py
panko/policies/base.py
panko/policies/segregation.py
panko/policies/telemetry.py
panko/publisher/__init__.py
panko/publisher/database.py
panko/storage/__init__.py
panko/storage/base.py
panko/storage/impl_elasticsearch.py
panko/storage/impl_hbase.py
panko/storage/impl_log.py
panko/storage/impl_mongodb.py
panko/storage/impl_sqlalchemy.py
panko/storage/models.py
panko/storage/pymongo_base.py
panko/storage/hbase/__init__.py
panko/storage/hbase/base.py
panko/storage/hbase/inmemory.py
panko/storage/hbase/utils.py
panko/storage/mongo/__init__.py
panko/storage/mongo/utils.py
panko/storage/sqlalchemy/__init__.py
panko/storage/sqlalchemy/models.py
panko/storage/sqlalchemy/alembic/README
panko/storage/sqlalchemy/alembic/alembic.ini
panko/storage/sqlalchemy/alembic/env.py
panko/storage/sqlalchemy/alembic/script.py.mako
panko/storage/sqlalchemy/alembic/versions/c3955547bff2_support_big_integer_traits.py
panko/tests/__init__.py
panko/tests/base.py
panko/tests/db.py
panko/tests/mocks.py
panko/tests/functional/__init__.py
panko/tests/functional/test_bin.py
panko/tests/functional/api/__init__.py
panko/tests/functional/api/v2/__init__.py
panko/tests/functional/api/v2/test_acl_scenarios.py
panko/tests/functional/api/v2/test_app.py
panko-10.0.0.dist-info/AUTHORS
panko-10.0.0.dist-info/LICENSE
panko-10.0.0.dist-info/METADATA
panko-10.0.0.dist-info/WHEEL
panko-10.0.0.dist-info/entry_points.txt
panko-10.0.0.dist-info/pbr.json
panko-10.0.0.dist-info/top_level.txt
panko-10.0.0.dist-info/RECORD
